ErwinJr2/SaveLoad.py
ErwinJr2/rFittings.py
ErwinJr2/Info.plist
ErwinJr2/__init__.py
ErwinJr2/versionAndName.py
ErwinJr2/Material.py
ErwinJr2/EJcanvas.py
ErwinJr2/genshortcut.py
ErwinJr2/customQTClass.py
ErwinJr2/QuantumTab.py
ErwinJr2/QCPlotter.py
ErwinJr2/QCLayers.py
ErwinJr2/__main__.py
ErwinJr2/OptStrata.py
ErwinJr2/ErwinJr.py
ErwinJr2/OpticalTab.py
ErwinJr2/darkDetect.py
ErwinJr2/OneDQuantum/Makefile
ErwinJr2/OneDQuantum/1DSchrodinger.h
ErwinJr2/OneDQuantum/band.h
ErwinJr2/OneDQuantum/OneDQuantum.sln
ErwinJr2/OneDQuantum/c_schrodinger.c
ErwinJr2/OneDQuantum/1DSchrodinger.vcxproj
ErwinJr2/OneDQuantum/science.h
ErwinJr2/OneDQuantum/1DSchrodinger.c
ErwinJr2/OneDQuantum/c_schrodinger.pyi
ErwinJr2/OneDQuantum/typeDefs.py
ErwinJr2/OneDQuantum/band.c
ErwinJr2/OneDQuantum/c_schrodinger.cpython-312-x86_64-linux-gnu.so
ErwinJr2/OneDQuantum/band.py
ErwinJr2/OneDQuantum/fftautocorr/fftautocorr.c
ErwinJr2/OneDQuantum/fftautocorr/fftautocorr.h
ErwinJr2/OneDQuantum/fftautocorr/factortable.h
ErwinJr2/OneDQuantum/fftautocorr/test.c
ErwinJr2/OneDQuantum/fftautocorr/tablegen.py
ErwinJr2/images/filequit.png
ErwinJr2/images/EJpng64.png
ErwinJr2/images/filesave.png
ErwinJr2/images/EJpng256.png
ErwinJr2/images/EJico.ico
ErwinJr2/images/EJpng32.png
ErwinJr2/images/fileopen.png
ErwinJr2/images/filesaveas.png
ErwinJr2/images/EJicns.icns
ErwinJr2/images/EJpng48.png
ErwinJr2/images/filenew.png
ErwinJr2/images/EJpng128.png
ErwinJr2/images/splash.png
ErwinJr2/example/PQLiu.json
ErwinJr2-2.2.9.post4.dist-info/LICENSE
ErwinJr2-2.2.9.post4.dist-info/WHEEL
ErwinJr2-2.2.9.post4.dist-info/METADATA
ErwinJr2-2.2.9.post4.dist-info/top_level.txt
ErwinJr2-2.2.9.post4.dist-info/RECORD
ErwinJr2-2.2.9.post4.dist-info/entry_points.txt
ErwinJr2.libs/libgomp-a34b3233.so.1.0.0
