Metadata-Version: 2.2
Name: ErwinJr2
Version: 2.2.9.post4
Summary: A Quantum Cascade Laser Design Tool
Author-email: Ming Lyu <caref.lm@gmail.com>
Project-URL: Docs: User Guide, https://erwinjr2.readthedocs.io/en/latest/
Project-URL: Source Code, https://github.com/ErwinJr2/ErwinJr2
Project-URL: homepage, https://github.com/ErwinJr2/ErwinJr2
Project-URL: Bug Tracker, https://github.com/ErwinJr2/ErwinJr2/issues
Keywords: Quantum Cascade Laser,Maxwell,Schrodinger,quantum
Classifier: Development Status :: 4 - Beta
Classifier: Environment :: Console
Classifier: Environment :: X11 Applications :: Qt
Classifier: Intended Audience :: Education
Classifier: License :: OSI Approved :: GNU General Public License v3 (GPLv3)
Classifier: Operating System :: POSIX :: Linux
Classifier: Operating System :: MacOS
Classifier: Operating System :: Microsoft :: Windows
Classifier: Programming Language :: C
Classifier: Programming Language :: Python
Classifier: Programming Language :: Python :: 3
Classifier: Programming Language :: Python :: 3 :: Only
Classifier: Topic :: Scientific/Engineering
Classifier: Topic :: Scientific/Engineering :: Electronic Design Automation (EDA)
Classifier: Topic :: Scientific/Engineering :: Physics
Classifier: Topic :: Scientific/Engineering :: Visualization
Requires-Python: >=3.9
License-File: LICENSE
Requires-Dist: numpy>=2.0.0
Requires-Dist: scipy
Provides-Extra: gui
Requires-Dist: pyqt5; extra == "gui"
Requires-Dist: matplotlib>=3.3; extra == "gui"
Requires-Dist: winshell; sys_platform == "win32" and extra == "gui"
Requires-Dist: pypiwin32; sys_platform == "win32" and extra == "gui"
Provides-Extra: dev
Requires-Dist: sphinx>=2; extra == "dev"
Requires-Dist: sphinx_rtd_theme; extra == "dev"
Requires-Dist: sphinxcontrib-bibtex>=2.0.0; extra == "dev"
Requires-Dist: breathe; extra == "dev"
